pyfort/__init__.py
pyfort/__main__.py
pyfort/menu.py
pyfort/pyfort.py
pyfort/test.py
pyfort/data/__init__.py
pyfort/data/db_test.py
pyfort/data/secret_key.py
pyfort/lib/__init__.py
pyfort/lib/secret_key.py
pyfort/secret/__init__.py
pyfort/secret/secret_json.py
pyfort/secret/secret_sqlite.py
pyfort/unittest/__init__.py
pyfort/unittest/test_fort.py
pyfort/unittest/lib/__init__.py
pyfort/utils/__init__.py
pyfort/utils/utils.py
pyfort-0.0.5.dist-info/LICENSE
pyfort-0.0.5.dist-info/METADATA
pyfort-0.0.5.dist-info/WHEEL
pyfort-0.0.5.dist-info/entry_points.txt
pyfort-0.0.5.dist-info/top_level.txt
pyfort-0.0.5.dist-info/RECORD
