Metadata-Version: 2.1
Name: pyfort
Version: 0.0.5
Summary: command-line password manager
Home-page: https://github.com/a-tharva/fort
Author: Atharva Bhandvalkar
Author-email: <atharv.bhandvalkar@gmail.com>
License: MIT
Keywords: python
Platform: UNKNOWN
Classifier: Development Status :: 4 - Beta
Classifier: Intended Audience :: Developers
Classifier: License :: OSI Approved :: MIT License
Classifier: Programming Language :: Python :: 3
Classifier: Operating System :: Unix
Classifier: Operating System :: MacOS :: MacOS X
Classifier: Operating System :: Microsoft :: Windows
Requires-Dist: colorama
Requires-Dist: termcolor
Requires-Dist: cryptography
